unused_path/__init__.py
unused_path/core.py
unused_path/helpers.py
unused_path/py.typed
unused_path-1.1.0.dist-info/METADATA
unused_path-1.1.0.dist-info/WHEEL
unused_path-1.1.0.dist-info/licenses/LICENSE
unused_path-1.1.0.dist-info/RECORD
