Metadata-Version: 2.4
Name: unused-path
Version: 1.1.0
Summary: Generate unused file and directory paths by auto-incrementing numeric suffixes. Similar to how browsers handle duplicate downloads.
Project-URL: Homepage, https://github.com/ysskrishna/unused-path
Project-URL: Repository, https://github.com/ysskrishna/unused-path.git
Project-URL: Issues, https://github.com/ysskrishna/unused-path/issues
Project-URL: Changelog, https://github.com/ysskrishna/unused-path/blob/main/CHANGELOG.md
Author-email: "Y. Siva Sai Krishna" <sivasaikrishnassk@gmail.com>
License: MIT
License-File: LICENSE
Keywords: avoid,conflict,directory,filename,increment,path,suffix,unique,unused,utilities,utils
Classifier: Development Status :: 4 - Beta
Classifier: Intended Audience :: Developers
Classifier: License :: OSI Approved :: MIT License
Classifier: Operating System :: OS Independent
Classifier: Programming Language :: Python :: 3
Classifier: Programming Language :: Python :: 3.8
Classifier: Programming Language :: Python :: 3.9
Classifier: Programming Language :: Python :: 3.10
Classifier: Programming Language :: Python :: 3.11
Classifier: Programming Language :: Python :: 3.12
Classifier: Topic :: Software Development :: Libraries :: Python Modules
Classifier: Topic :: Utilities
Classifier: Typing :: Typed
Requires-Python: >=3.8
